{
  "blade": {
    "title": "Клиенты",
    "error": "Ошибка",
    "subtitle": ""
  },
  "clients": {
    "blades" : {
      "member-list": {
        "title": "Клиенты",
        "keywordType": "Выберите критерий",
        "labels": {
          "phone": "Телефон",
          "name": "Имя",
          "lastName": "Фамилия",
          "nPassport":"Номер паспорта",
          "nContract":"Номер контракта",
          "email":"Email",
          "nCar":"Номер машины"
        }
      },
      "member-add": {
        "menu": {
          "clients": {
            "title": "Создать клиента",
            "description":""
          }
        }
      }
    }
  },


  "modules": {
    "blades": {
      "clients": {
        "title": "Клиенты"
      }
    },
    "menu": {
      "clients": "Клиенты"
    }
  }
}